medscheduler/__init__.py
medscheduler/constants.py
medscheduler/py.typed
medscheduler/scheduler.py
medscheduler/utils/__init__.py
medscheduler/utils/plotting.py
medscheduler/utils/reference_data_utils.py
medscheduler-0.2.2.dist-info/licenses/LICENSE
medscheduler-0.2.2.dist-info/METADATA
medscheduler-0.2.2.dist-info/WHEEL
medscheduler-0.2.2.dist-info/top_level.txt
medscheduler-0.2.2.dist-info/RECORD
