Metadata-Version: 2.4
Name: medscheduler
Version: 0.2.2
Summary: Synthetic outpatient scheduling dataset generator (slots, patients, appointments).
Author: Carolina González Galtier
License-Expression: MIT
Project-URL: repository, https://github.com/carogaltier/medscheduler
Project-URL: bug_tracker, https://github.com/carogaltier/medscheduler/issues
Keywords: healthcare,synthetic-data,appointments,scheduling,outpatient,simulation
Classifier: Development Status :: 3 - Alpha
Classifier: Intended Audience :: Developers
Classifier: Programming Language :: Python :: 3
Classifier: Programming Language :: Python :: 3.9
Classifier: Programming Language :: Python :: 3.10
Classifier: Programming Language :: Python :: 3.11
Classifier: Operating System :: OS Independent
Classifier: Topic :: Scientific/Engineering
Classifier: Topic :: Software Development :: Libraries :: Python Modules
Classifier: Typing :: Typed
Requires-Python: >=3.9
License-File: LICENSE
Requires-Dist: pandas>=1.5.0
Requires-Dist: numpy>=1.21.0
Requires-Dist: faker>=18.0.0
Provides-Extra: viz
Requires-Dist: matplotlib>=3.5; extra == "viz"
Provides-Extra: dev
Requires-Dist: pytest>=7.0; extra == "dev"
Requires-Dist: pytest-cov>=4.0; extra == "dev"
Requires-Dist: ruff>=0.5; extra == "dev"
Requires-Dist: mypy>=1.7; extra == "dev"
Requires-Dist: build; extra == "dev"
Requires-Dist: twine; extra == "dev"
Dynamic: license-file
